{
  "data": {
    "getViewFields": {
      "data": [
        {
          "id": "8335761",
          "label": "title",
          "matchKey": "title",
          "matchKeySub": null,
          "matchMeta": null,
          "order": 0,
          "previewData": [
            "GOT S1 Trailer",
            "GOT S2 Trailer",
            "GOT S3 Trailer",
            "GOT S4 Trailer",
            "GOT S5 Trailer",
            "SLXAlpha - UI Centric video",
            "SLXAlpha - Imagen video",
            "SLXAlpha - Rakuten video",
            "SLXAlpha -  Amagi video"
          ],
          "confirmed": false,
          "ignored": false,
          "suggestedMatchKey": [
            "title",
            "title_short",
            "title_medium",
            "title_long"
          ],
          "columnDensity": 13,
          "totalRows": 13
        },
        {
          "id": "8335762",
          "label": "skylark_object_type",
          "matchKey": null,
          "matchKeySub": null,
          "matchMeta": null,
          "order": 1,
          "previewData": [
            "assets",
            "assets",
            "assets",
            "assets",
            "assets",
            "assets",
            "assets",
            "assets",
            "assets"
          ],
          "confirmed": false,
          "ignored": true,
          "suggestedMatchKey": [],
          "columnDensity": 13,
          "totalRows": 13
        },
        {
          "id": "8335763",
          "label": "asset_type",
          "matchKey": null,
          "matchKeySub": null,
          "matchMeta": null,
          "order": 2,
          "previewData": [
            "Trailer",
            "Trailer",
            "Trailer",
            "Trailer",
            "Trailer",
            "Main",
            "Main",
            "Main",
            "Main"
          ],
          "confirmed": false,
          "ignored": true,
          "suggestedMatchKey": [],
          "columnDensity": 13,
          "totalRows": 13
        },
        {
          "id": "8335764",
          "label": "file",
          "matchKey": null,
          "matchKeySub": null,
          "matchMeta": null,
          "order": 3,
          "previewData": [
            "S01_trailer.mp4 (https://dl.airtable.com/.attachments/c9e53e0098a2ffcb6ab34a3a79cbd8d7/3576707a/S01_trailer.mp4)",
            "S02_trailer.mp4 (https://dl.airtable.com/.attachments/65af7b331593deb9a59494403387c7d4/7e8cc908/S02_trailer.mp4)",
            "S03_trailer.mp4 (https://dl.airtable.com/.attachments/96690ff8004897fed2326601b088fc5b/34f559ba/S03_trailer.mp4)",
            "S04_trailer.mp4 (https://dl.airtable.com/.attachments/38fcf3531443f4c6b2bfe6c25b2fdbbb/b521d6bd/S04_trailer.mp4)",
            "S05_trailer.mp4 (https://dl.airtable.com/.attachments/63e4dee1362f76cbd52511170035a69f/acc4b121/S05_trailer.mp4)"
          ],
          "confirmed": false,
          "ignored": false,
          "suggestedMatchKey": ["data_source_fields"],
          "columnDensity": 5,
          "totalRows": 13
        },
        {
          "id": "8335765",
          "label": "External Asset URL",
          "matchKey": null,
          "matchKeySub": null,
          "matchMeta": null,
          "order": 4,
          "previewData": [
            "https://dl.airtable.com/.attachments/ba3f79f1197efbf96cb597e78fdee4cf/43409a61/tvs-phfi-jkv2022-10-1311_14GMT1.mp4",
            "https://dl.airtable.com/.attachments/283b897fcae496e192933e0935f21b62/d92158ae/SkylarkImagendemos2022-10-1714_08GMT1.mp4",
            "https://dl.airtable.com/.attachments/0d474922e8b1ef8135ebc849089abe7e/abc18a5a/SkylarkXAlphaIntro2022-10-1811_02GMT1.mp4",
            "https://dl.airtable.com/.attachments/0940fce8611a1eeae9b95fdc5d9ad7f3/258c3c56/Amagi-SkylarkXAlphaIntro2022-10-1817_12GMT1.mp4",
            "https://dl.airtable.com/.attachments/937ec3c3e07067430ec54d0ff73842c2/8bfe961e/SkylarkXAlphaIntro2022-10-1914_04GMT1.mp4",
            "https://dl.airtable.com/.attachments/152722437c4f0b582c27ce728086046c/65e6cecf/SkylarkXAlphaDemo2022-10-1916_04GMT1.mp4",
            "https://dl.airtable.com/.attachments/2773381ab45e9f72b9ec75c82cb03b99/b6d8a797/SkylarkXAlphaIntro-Ost22022-10-2013_05GMT1.mp4",
            "https://dl.airtable.com/.attachments/758f3809629d442e2de90a844f5bc607/253c886e/Mux_SkylarkXAlphaintroduction2022-10-2016_33GMT1.mp4"
          ],
          "confirmed": false,
          "ignored": true,
          "suggestedMatchKey": [],
          "columnDensity": 8,
          "totalRows": 13
        },
        {
          "id": "8335766",
          "label": "url",
          "matchKey": null,
          "matchKeySub": null,
          "matchMeta": null,
          "order": 5,
          "previewData": [
            "https://dl.airtable.com/.attachments/c9e53e0098a2ffcb6ab34a3a79cbd8d7/3576707a/S01_trailer.mp4",
            "https://dl.airtable.com/.attachments/65af7b331593deb9a59494403387c7d4/7e8cc908/S02_trailer.mp4",
            "https://dl.airtable.com/.attachments/96690ff8004897fed2326601b088fc5b/34f559ba/S03_trailer.mp4",
            "https://dl.airtable.com/.attachments/38fcf3531443f4c6b2bfe6c25b2fdbbb/b521d6bd/S04_trailer.mp4",
            "https://dl.airtable.com/.attachments/63e4dee1362f76cbd52511170035a69f/acc4b121/S05_trailer.mp4",
            "https://dl.airtable.com/.attachments/ba3f79f1197efbf96cb597e78fdee4cf/43409a61/tvs-phfi-jkv2022-10-1311_14GMT1.mp4",
            "https://dl.airtable.com/.attachments/283b897fcae496e192933e0935f21b62/d92158ae/SkylarkImagendemos2022-10-1714_08GMT1.mp4",
            "https://dl.airtable.com/.attachments/0d474922e8b1ef8135ebc849089abe7e/abc18a5a/SkylarkXAlphaIntro2022-10-1811_02GMT1.mp4",
            "https://dl.airtable.com/.attachments/0940fce8611a1eeae9b95fdc5d9ad7f3/258c3c56/Amagi-SkylarkXAlphaIntro2022-10-1817_12GMT1.mp4"
          ],
          "confirmed": false,
          "ignored": true,
          "suggestedMatchKey": [],
          "columnDensity": 13,
          "totalRows": 13
        },
        {
          "id": "8335767",
          "label": "parent",
          "matchKey": null,
          "matchKeySub": null,
          "matchMeta": null,
          "order": 6,
          "previewData": [
            "GOT S01E1 - Winter is Coming",
            "GOT S02E1 - The North Remembers",
            "GOT S03E1 - Valar Dohaeris",
            "GOT S04E1 - Two Swords",
            "GOT S05E1 - The Wars to Come",
            "SLXAlpha - UI Centric",
            "SLXAlpha - Imagen",
            "SLXAlpha - Rakuten",
            "SLXAlpha - Amagi"
          ],
          "confirmed": false,
          "ignored": true,
          "suggestedMatchKey": [],
          "columnDensity": 13,
          "totalRows": 13
        },
        {
          "id": "8335768",
          "label": "slug",
          "matchKey": "slug",
          "matchKeySub": null,
          "matchMeta": null,
          "order": 7,
          "previewData": [
            "got-s1-trailer",
            "got-s2-trailer",
            "got-s3-trailer",
            "got-s4-trailer",
            "got-s5-trailer",
            "ui-centric-alpha-demo-main",
            "imagen-alpha-demo-main",
            "rakuten-alpha-demo-main",
            "amagi-alpha-demo-main"
          ],
          "confirmed": false,
          "ignored": false,
          "suggestedMatchKey": ["slug"],
          "columnDensity": 13,
          "totalRows": 13
        },
        {
          "id": "8335769",
          "label": "release_date",
          "matchKey": "release_date",
          "matchKeySub": null,
          "matchMeta": null,
          "order": 8,
          "previewData": [
            "17/4/2011",
            "1/4/2012",
            "31/3/2013",
            "6/4/2014",
            "12/4/2015",
            "13/10/2022",
            "17/10/2022",
            "18/10/2022",
            "18/10/2022"
          ],
          "confirmed": false,
          "ignored": false,
          "suggestedMatchKey": ["release_date"],
          "columnDensity": 13,
          "totalRows": 13
        },
        {
          "id": "8335770",
          "label": "images",
          "matchKey": null,
          "matchKeySub": null,
          "matchMeta": null,
          "order": 9,
          "previewData": [
            "GOT - S1 - 1.jpg",
            "GOT - S2 - 10.jpg",
            "GOT - S3 - 1.jpg",
            "GOT - S4 - 1.jpg",
            "GOT - S5 - 1.jpg"
          ],
          "confirmed": false,
          "ignored": true,
          "suggestedMatchKey": [],
          "columnDensity": 5,
          "totalRows": 13
        },
        {
          "id": "8335771",
          "label": "images (preview)",
          "matchKey": null,
          "matchKeySub": null,
          "matchMeta": null,
          "order": 10,
          "previewData": [
            "GOT - S1 - 1.jpg (https://dl.airtable.com/.attachments/c8b23d45c55cf09081954dd208dcce4b/80b72296/GOT-S1-1.jpg)",
            "GOT - S2 - 10.jpg (https://dl.airtable.com/.attachments/ce178d79217d15f7518d9829c0fcf9b3/1be9b2d0/GOT-S2-10.jpg)",
            "GOT - S3 - 1.jpg (https://dl.airtable.com/.attachments/c3d99b1ef47ff6b150590f59e868463c/648db995/GOT-S3-1.jpg)",
            "GOT - S4 - 1.jpg (https://dl.airtable.com/.attachments/777fef933dd3373f4291f2215fa48cc4/3c6ff093/GOT-S4-1.jpg)",
            "GOT - S5 - 1.jpg (https://dl.airtable.com/.attachments/ee29386ac3fc77cb2935e0959810276b/69e0dc31/GOT-S5-1.jpg)"
          ],
          "confirmed": false,
          "ignored": true,
          "suggestedMatchKey": [],
          "columnDensity": 5,
          "totalRows": 13
        },
        {
          "id": "8335772",
          "label": "ratings",
          "matchKey": null,
          "matchKeySub": null,
          "matchMeta": null,
          "order": 11,
          "previewData": ["18", "18", "18", "18", "18"],
          "confirmed": false,
          "ignored": true,
          "suggestedMatchKey": [],
          "columnDensity": 5,
          "totalRows": 13
        },
        {
          "id": "8335773",
          "label": "availability",
          "matchKey": null,
          "matchKeySub": null,
          "matchMeta": null,
          "order": 12,
          "previewData": [],
          "confirmed": false,
          "ignored": true,
          "suggestedMatchKey": [],
          "columnDensity": 0,
          "totalRows": 13
        },
        {
          "id": "8335774",
          "label": "title_short",
          "matchKey": "title_short",
          "matchKeySub": null,
          "matchMeta": null,
          "order": 13,
          "previewData": [],
          "confirmed": false,
          "ignored": false,
          "suggestedMatchKey": ["title_short", "title_long"],
          "columnDensity": 0,
          "totalRows": 13
        },
        {
          "id": "8335775",
          "label": "title_medium",
          "matchKey": "title_medium",
          "matchKeySub": null,
          "matchMeta": null,
          "order": 14,
          "previewData": [],
          "confirmed": false,
          "ignored": false,
          "suggestedMatchKey": ["title_medium", "synopsis_medium"],
          "columnDensity": 0,
          "totalRows": 13
        },
        {
          "id": "8335776",
          "label": "title_long",
          "matchKey": "title_long",
          "matchKeySub": null,
          "matchMeta": null,
          "order": 15,
          "previewData": [],
          "confirmed": false,
          "ignored": false,
          "suggestedMatchKey": ["title_long", "title_short", "title_medium"],
          "columnDensity": 0,
          "totalRows": 13
        },
        {
          "id": "8335777",
          "label": "synopsis_short",
          "matchKey": "synopsis_short",
          "matchKeySub": null,
          "matchMeta": null,
          "order": 16,
          "previewData": [],
          "confirmed": false,
          "ignored": false,
          "suggestedMatchKey": [
            "synopsis_short",
            "synopsis_long",
            "synopsis_medium"
          ],
          "columnDensity": 0,
          "totalRows": 13
        },
        {
          "id": "8335778",
          "label": "synopsis_medium",
          "matchKey": "synopsis_medium",
          "matchKeySub": null,
          "matchMeta": null,
          "order": 17,
          "previewData": [],
          "confirmed": false,
          "ignored": false,
          "suggestedMatchKey": [
            "synopsis_medium",
            "synopsis_short",
            "synopsis_long"
          ],
          "columnDensity": 0,
          "totalRows": 13
        },
        {
          "id": "8335779",
          "label": "synopsis_long",
          "matchKey": "synopsis_long",
          "matchKeySub": null,
          "matchMeta": null,
          "order": 18,
          "previewData": [],
          "confirmed": false,
          "ignored": false,
          "suggestedMatchKey": [
            "synopsis_long",
            "synopsis_short",
            "synopsis_medium"
          ],
          "columnDensity": 0,
          "totalRows": 13
        },
        {
          "id": "8335780",
          "label": "credits",
          "matchKey": null,
          "matchKeySub": null,
          "matchMeta": null,
          "order": 19,
          "previewData": [],
          "confirmed": false,
          "ignored": true,
          "suggestedMatchKey": [],
          "columnDensity": 0,
          "totalRows": 13
        },
        {
          "id": "8335781",
          "label": "genres",
          "matchKey": null,
          "matchKeySub": null,
          "matchMeta": null,
          "order": 20,
          "previewData": [],
          "confirmed": false,
          "ignored": true,
          "suggestedMatchKey": [],
          "columnDensity": 0,
          "totalRows": 13
        },
        {
          "id": "8335782",
          "label": "themes",
          "matchKey": null,
          "matchKeySub": null,
          "matchMeta": null,
          "order": 21,
          "previewData": [],
          "confirmed": false,
          "ignored": true,
          "suggestedMatchKey": [],
          "columnDensity": 0,
          "totalRows": 13
        },
        {
          "id": "8335783",
          "label": "external_asset_data_source_id",
          "matchKey": null,
          "matchKeySub": null,
          "matchMeta": null,
          "order": 22,
          "previewData": [],
          "confirmed": false,
          "ignored": true,
          "suggestedMatchKey": [],
          "columnDensity": 0,
          "totalRows": 13
        }
      ],
      "validation": []
    }
  }
}
